{
  "$defs": {
    "BrokerAccountActionResponse": {
      "additionalProperties": false,
      "properties": {
        "accountId": {
          "maxLength": 128,
          "minLength": 1,
          "title": "Accountid",
          "type": "string"
        },
        "action": {
          "enum": [
            "reconnect",
            "pause_sync",
            "resume_sync",
            "refresh",
            "acknowledge_alert",
            "update_trading_policy",
            "update_allocation"
          ],
          "title": "Action",
          "type": "string"
        },
        "actionId": {
          "maxLength": 128,
          "minLength": 1,
          "title": "Actionid",
          "type": "string"
        },
        "message": {
          "anyOf": [
            {
              "type": "string"
            },
            {
              "type": "null"
            }
          ],
          "default": null,
          "title": "Message"
        },
        "requestedAt": {
          "format": "date-time",
          "title": "Requestedat",
          "type": "string"
        },
        "resultingConnectionHealth": {
          "anyOf": [
            {
              "$ref": "#/$defs/BrokerConnectionHealth"
            },
            {
              "type": "null"
            }
          ],
          "default": null
        },
        "status": {
          "default": "accepted",
          "enum": [
            "accepted",
            "in_progress",
            "completed",
            "failed"
          ],
          "title": "Status",
          "type": "string"
        },
        "syncPaused": {
          "anyOf": [
            {
              "type": "boolean"
            },
            {
              "type": "null"
            }
          ],
          "default": null,
          "title": "Syncpaused"
        },
        "tradeReadiness": {
          "anyOf": [
            {
              "enum": [
                "ready",
                "review",
                "blocked"
              ],
              "type": "string"
            },
            {
              "type": "null"
            }
          ],
          "default": null,
          "title": "Tradereadiness"
        }
      },
      "required": [
        "actionId",
        "accountId",
        "action",
        "requestedAt"
      ],
      "title": "BrokerAccountActionResponse",
      "type": "object"
    },
    "BrokerAccountConfiguration": {
      "additionalProperties": false,
      "properties": {
        "accountId": {
          "maxLength": 128,
          "minLength": 1,
          "title": "Accountid",
          "type": "string"
        },
        "accountName": {
          "anyOf": [
            {
              "maxLength": 128,
              "minLength": 1,
              "type": "string"
            },
            {
              "type": "null"
            }
          ],
          "default": null,
          "title": "Accountname"
        },
        "allocation": {
          "$ref": "#/$defs/BrokerStrategyAllocationSummary"
        },
        "audit": {
          "items": {
            "$ref": "#/$defs/BrokerAccountConfigurationAuditRecord"
          },
          "title": "Audit",
          "type": "array"
        },
        "baseCurrency": {
          "default": "USD",
          "maxLength": 3,
          "minLength": 3,
          "title": "Basecurrency",
          "type": "string"
        },
        "capabilities": {
          "$ref": "#/$defs/BrokerCapabilityFlags"
        },
        "configurationVersion": {
          "default": 1,
          "minimum": 1,
          "title": "Configurationversion",
          "type": "integer"
        },
        "effectivePolicy": {
          "$ref": "#/$defs/BrokerTradingPolicy"
        },
        "requestedPolicy": {
          "$ref": "#/$defs/BrokerTradingPolicy"
        },
        "updatedAt": {
          "anyOf": [
            {
              "format": "date-time",
              "type": "string"
            },
            {
              "type": "null"
            }
          ],
          "default": null,
          "title": "Updatedat"
        },
        "updatedBy": {
          "anyOf": [
            {
              "maxLength": 128,
              "minLength": 1,
              "type": "string"
            },
            {
              "type": "null"
            }
          ],
          "default": null,
          "title": "Updatedby"
        },
        "warnings": {
          "items": {
            "type": "string"
          },
          "title": "Warnings",
          "type": "array"
        }
      },
      "required": [
        "accountId"
      ],
      "title": "BrokerAccountConfiguration",
      "type": "object"
    },
    "BrokerAccountConfigurationAuditRecord": {
      "additionalProperties": false,
      "properties": {
        "accountId": {
          "maxLength": 128,
          "minLength": 1,
          "title": "Accountid",
          "type": "string"
        },
        "actor": {
          "anyOf": [
            {
              "maxLength": 128,
              "minLength": 1,
              "type": "string"
            },
            {
              "type": "null"
            }
          ],
          "default": null,
          "title": "Actor"
        },
        "after": {
          "additionalProperties": true,
          "title": "After",
          "type": "object"
        },
        "auditId": {
          "maxLength": 128,
          "minLength": 1,
          "title": "Auditid",
          "type": "string"
        },
        "before": {
          "additionalProperties": true,
          "title": "Before",
          "type": "object"
        },
        "category": {
          "enum": [
            "trading_policy",
            "allocation",
            "onboarding"
          ],
          "title": "Category",
          "type": "string"
        },
        "denialReason": {
          "anyOf": [
            {
              "type": "string"
            },
            {
              "type": "null"
            }
          ],
          "default": null,
          "title": "Denialreason"
        },
        "grantedRoles": {
          "items": {
            "type": "string"
          },
          "title": "Grantedroles",
          "type": "array"
        },
        "outcome": {
          "default": "saved",
          "enum": [
            "saved",
            "denied",
            "warning"
          ],
          "title": "Outcome",
          "type": "string"
        },
        "requestId": {
          "anyOf": [
            {
              "maxLength": 160,
              "minLength": 1,
              "type": "string"
            },
            {
              "type": "null"
            }
          ],
          "default": null,
          "title": "Requestid"
        },
        "requestedAt": {
          "format": "date-time",
          "title": "Requestedat",
          "type": "string"
        },
        "summary": {
          "default": "",
          "title": "Summary",
          "type": "string"
        }
      },
      "required": [
        "auditId",
        "accountId",
        "category",
        "requestedAt"
      ],
      "title": "BrokerAccountConfigurationAuditRecord",
      "type": "object"
    },
    "BrokerAccountSummary": {
      "additionalProperties": false,
      "properties": {
        "accountId": {
          "maxLength": 128,
          "minLength": 1,
          "title": "Accountid",
          "type": "string"
        },
        "accountNumberMasked": {
          "anyOf": [
            {
              "maxLength": 32,
              "minLength": 1,
              "type": "string"
            },
            {
              "type": "null"
            }
          ],
          "default": null,
          "title": "Accountnumbermasked"
        },
        "activePortfolioName": {
          "anyOf": [
            {
              "maxLength": 128,
              "minLength": 1,
              "type": "string"
            },
            {
              "type": "null"
            }
          ],
          "default": null,
          "title": "Activeportfolioname"
        },
        "alertCount": {
          "default": 0,
          "minimum": 0,
          "title": "Alertcount",
          "type": "integer"
        },
        "allocationSummary": {
          "anyOf": [
            {
              "$ref": "#/$defs/BrokerStrategyAllocationSummary"
            },
            {
              "type": "null"
            }
          ],
          "default": null
        },
        "baseCurrency": {
          "default": "USD",
          "maxLength": 3,
          "minLength": 3,
          "title": "Basecurrency",
          "type": "string"
        },
        "broker": {
          "enum": [
            "alpaca",
            "schwab",
            "etrade",
            "kalshi"
          ],
          "title": "Broker",
          "type": "string"
        },
        "buyingPower": {
          "default": 0.0,
          "title": "Buyingpower",
          "type": "number"
        },
        "cash": {
          "default": 0.0,
          "title": "Cash",
          "type": "number"
        },
        "configurationVersion": {
          "anyOf": [
            {
              "minimum": 1,
              "type": "integer"
            },
            {
              "type": "null"
            }
          ],
          "default": null,
          "title": "Configurationversion"
        },
        "connectionHealth": {
          "$ref": "#/$defs/BrokerConnectionHealth"
        },
        "equity": {
          "default": 0.0,
          "title": "Equity",
          "type": "number"
        },
        "highestAlertSeverity": {
          "anyOf": [
            {
              "enum": [
                "info",
                "warning",
                "critical"
              ],
              "type": "string"
            },
            {
              "type": "null"
            }
          ],
          "default": null,
          "title": "Highestalertseverity"
        },
        "lastSyncedAt": {
          "anyOf": [
            {
              "format": "date-time",
              "type": "string"
            },
            {
              "type": "null"
            }
          ],
          "default": null,
          "title": "Lastsyncedat"
        },
        "name": {
          "maxLength": 128,
          "minLength": 1,
          "title": "Name",
          "type": "string"
        },
        "openOrderCount": {
          "default": 0,
          "minimum": 0,
          "title": "Openordercount",
          "type": "integer"
        },
        "openPositionCount": {
          "default": 0,
          "minimum": 0,
          "title": "Openpositioncount",
          "type": "integer"
        },
        "overallStatus": {
          "default": "warning",
          "enum": [
            "healthy",
            "warning",
            "critical"
          ],
          "title": "Overallstatus",
          "type": "string"
        },
        "snapshotAsOf": {
          "anyOf": [
            {
              "format": "date-time",
              "type": "string"
            },
            {
              "type": "null"
            }
          ],
          "default": null,
          "title": "Snapshotasof"
        },
        "strategyLabel": {
          "anyOf": [
            {
              "maxLength": 128,
              "minLength": 1,
              "type": "string"
            },
            {
              "type": "null"
            }
          ],
          "default": null,
          "title": "Strategylabel"
        },
        "tradeReadiness": {
          "default": "review",
          "enum": [
            "ready",
            "review",
            "blocked"
          ],
          "title": "Tradereadiness",
          "type": "string"
        },
        "tradeReadinessReason": {
          "anyOf": [
            {
              "type": "string"
            },
            {
              "type": "null"
            }
          ],
          "default": null,
          "title": "Tradereadinessreason"
        }
      },
      "required": [
        "accountId",
        "broker",
        "name"
      ],
      "title": "BrokerAccountSummary",
      "type": "object"
    },
    "BrokerCapabilityFlags": {
      "additionalProperties": false,
      "properties": {
        "canAcknowledgeAlerts": {
          "default": false,
          "title": "Canacknowledgealerts",
          "type": "boolean"
        },
        "canPauseSync": {
          "default": false,
          "title": "Canpausesync",
          "type": "boolean"
        },
        "canReadAllocation": {
          "default": false,
          "title": "Canreadallocation",
          "type": "boolean"
        },
        "canReadBalances": {
          "default": false,
          "title": "Canreadbalances",
          "type": "boolean"
        },
        "canReadOrders": {
          "default": false,
          "title": "Canreadorders",
          "type": "boolean"
        },
        "canReadPositions": {
          "default": false,
          "title": "Canreadpositions",
          "type": "boolean"
        },
        "canReadTradingPolicy": {
          "default": false,
          "title": "Canreadtradingpolicy",
          "type": "boolean"
        },
        "canReconnect": {
          "default": false,
          "title": "Canreconnect",
          "type": "boolean"
        },
        "canRefresh": {
          "default": false,
          "title": "Canrefresh",
          "type": "boolean"
        },
        "canReleaseTradeConfirmation": {
          "default": false,
          "title": "Canreleasetradeconfirmation",
          "type": "boolean"
        },
        "canTrade": {
          "default": false,
          "title": "Cantrade",
          "type": "boolean"
        },
        "canWriteAllocation": {
          "default": false,
          "title": "Canwriteallocation",
          "type": "boolean"
        },
        "canWriteTradingPolicy": {
          "default": false,
          "title": "Canwritetradingpolicy",
          "type": "boolean"
        },
        "readOnlyReason": {
          "anyOf": [
            {
              "type": "string"
            },
            {
              "type": "null"
            }
          ],
          "default": null,
          "title": "Readonlyreason"
        }
      },
      "title": "BrokerCapabilityFlags",
      "type": "object"
    },
    "BrokerConnectionHealth": {
      "additionalProperties": false,
      "properties": {
        "authExpiresAt": {
          "anyOf": [
            {
              "format": "date-time",
              "type": "string"
            },
            {
              "type": "null"
            }
          ],
          "default": null,
          "title": "Authexpiresat"
        },
        "authStatus": {
          "default": "not_connected",
          "enum": [
            "authenticated",
            "expires_soon",
            "expired",
            "reauth_required",
            "not_connected"
          ],
          "title": "Authstatus",
          "type": "string"
        },
        "connectionState": {
          "default": "disconnected",
          "enum": [
            "connected",
            "degraded",
            "disconnected",
            "reconnect_required"
          ],
          "title": "Connectionstate",
          "type": "string"
        },
        "failureMessage": {
          "anyOf": [
            {
              "type": "string"
            },
            {
              "type": "null"
            }
          ],
          "default": null,
          "title": "Failuremessage"
        },
        "lastCheckedAt": {
          "anyOf": [
            {
              "format": "date-time",
              "type": "string"
            },
            {
              "type": "null"
            }
          ],
          "default": null,
          "title": "Lastcheckedat"
        },
        "lastFailedSyncAt": {
          "anyOf": [
            {
              "format": "date-time",
              "type": "string"
            },
            {
              "type": "null"
            }
          ],
          "default": null,
          "title": "Lastfailedsyncat"
        },
        "lastSuccessfulSyncAt": {
          "anyOf": [
            {
              "format": "date-time",
              "type": "string"
            },
            {
              "type": "null"
            }
          ],
          "default": null,
          "title": "Lastsuccessfulsyncat"
        },
        "overallStatus": {
          "default": "warning",
          "enum": [
            "healthy",
            "warning",
            "critical"
          ],
          "title": "Overallstatus",
          "type": "string"
        },
        "staleReason": {
          "anyOf": [
            {
              "type": "string"
            },
            {
              "type": "null"
            }
          ],
          "default": null,
          "title": "Stalereason"
        },
        "syncPaused": {
          "default": false,
          "title": "Syncpaused",
          "type": "boolean"
        },
        "syncStatus": {
          "default": "never_synced",
          "enum": [
            "fresh",
            "stale",
            "syncing",
            "paused",
            "failed",
            "never_synced"
          ],
          "title": "Syncstatus",
          "type": "string"
        }
      },
      "title": "BrokerConnectionHealth",
      "type": "object"
    },
    "BrokerPositionSizeLimit": {
      "additionalProperties": false,
      "properties": {
        "mode": {
          "default": "pct_of_allocatable_capital",
          "enum": [
            "pct_of_allocatable_capital",
            "notional_base_ccy"
          ],
          "title": "Mode",
          "type": "string"
        },
        "value": {
          "exclusiveMinimum": 0.0,
          "title": "Value",
          "type": "number"
        }
      },
      "required": [
        "value"
      ],
      "title": "BrokerPositionSizeLimit",
      "type": "object"
    },
    "BrokerStrategyAllocationItem": {
      "additionalProperties": false,
      "properties": {
        "allocationMode": {
          "default": "percent",
          "enum": [
            "percent",
            "notional_base_ccy"
          ],
          "title": "Allocationmode",
          "type": "string"
        },
        "derivedWeightPct": {
          "anyOf": [
            {
              "maximum": 100.0,
              "minimum": 0.0,
              "type": "number"
            },
            {
              "type": "null"
            }
          ],
          "default": null,
          "title": "Derivedweightpct"
        },
        "enabled": {
          "default": true,
          "title": "Enabled",
          "type": "boolean"
        },
        "notes": {
          "default": "",
          "title": "Notes",
          "type": "string"
        },
        "sleeveId": {
          "maxLength": 128,
          "minLength": 1,
          "title": "Sleeveid",
          "type": "string"
        },
        "sleeveName": {
          "default": "",
          "title": "Sleevename",
          "type": "string"
        },
        "strategy": {
          "$ref": "#/$defs/BrokerStrategyReference"
        },
        "targetNotionalBaseCcy": {
          "anyOf": [
            {
              "exclusiveMinimum": 0.0,
              "type": "number"
            },
            {
              "type": "null"
            }
          ],
          "default": null,
          "title": "Targetnotionalbaseccy"
        },
        "targetWeightPct": {
          "anyOf": [
            {
              "maximum": 100.0,
              "minimum": 0.0,
              "type": "number"
            },
            {
              "type": "null"
            }
          ],
          "default": null,
          "title": "Targetweightpct"
        }
      },
      "required": [
        "sleeveId",
        "strategy"
      ],
      "title": "BrokerStrategyAllocationItem",
      "type": "object"
    },
    "BrokerStrategyAllocationSummary": {
      "additionalProperties": false,
      "properties": {
        "allocatableCapital": {
          "anyOf": [
            {
              "minimum": 0.0,
              "type": "number"
            },
            {
              "type": "null"
            }
          ],
          "default": null,
          "title": "Allocatablecapital"
        },
        "allocatedNotionalBaseCcy": {
          "anyOf": [
            {
              "minimum": 0.0,
              "type": "number"
            },
            {
              "type": "null"
            }
          ],
          "default": null,
          "title": "Allocatednotionalbaseccy"
        },
        "allocatedPercent": {
          "anyOf": [
            {
              "maximum": 100.01,
              "minimum": 0.0,
              "type": "number"
            },
            {
              "type": "null"
            }
          ],
          "default": null,
          "title": "Allocatedpercent"
        },
        "allocationMode": {
          "default": "percent",
          "enum": [
            "percent",
            "notional_base_ccy"
          ],
          "title": "Allocationmode",
          "type": "string"
        },
        "effectiveFrom": {
          "anyOf": [
            {
              "format": "date",
              "type": "string"
            },
            {
              "type": "null"
            }
          ],
          "default": null,
          "title": "Effectivefrom"
        },
        "items": {
          "items": {
            "$ref": "#/$defs/BrokerStrategyAllocationItem"
          },
          "title": "Items",
          "type": "array"
        },
        "portfolioName": {
          "anyOf": [
            {
              "maxLength": 128,
              "minLength": 1,
              "type": "string"
            },
            {
              "type": "null"
            }
          ],
          "default": null,
          "title": "Portfolioname"
        },
        "portfolioVersion": {
          "anyOf": [
            {
              "minimum": 1,
              "type": "integer"
            },
            {
              "type": "null"
            }
          ],
          "default": null,
          "title": "Portfolioversion"
        },
        "remainingNotionalBaseCcy": {
          "anyOf": [
            {
              "minimum": 0.0,
              "type": "number"
            },
            {
              "type": "null"
            }
          ],
          "default": null,
          "title": "Remainingnotionalbaseccy"
        },
        "remainingPercent": {
          "anyOf": [
            {
              "maximum": 100.01,
              "minimum": 0.0,
              "type": "number"
            },
            {
              "type": "null"
            }
          ],
          "default": null,
          "title": "Remainingpercent"
        },
        "sharedActivePortfolio": {
          "default": false,
          "title": "Sharedactiveportfolio",
          "type": "boolean"
        }
      },
      "title": "BrokerStrategyAllocationSummary",
      "type": "object"
    },
    "BrokerStrategyReference": {
      "additionalProperties": false,
      "properties": {
        "strategyName": {
          "maxLength": 128,
          "minLength": 1,
          "title": "Strategyname",
          "type": "string"
        },
        "strategyVersion": {
          "minimum": 1,
          "title": "Strategyversion",
          "type": "integer"
        }
      },
      "required": [
        "strategyName",
        "strategyVersion"
      ],
      "title": "BrokerStrategyReference",
      "type": "object"
    },
    "BrokerTradingPolicy": {
      "additionalProperties": false,
      "properties": {
        "allowedAssetClasses": {
          "items": {
            "enum": [
              "equity",
              "option"
            ],
            "type": "string"
          },
          "title": "Allowedassetclasses",
          "type": "array"
        },
        "allowedSides": {
          "items": {
            "enum": [
              "long",
              "short"
            ],
            "type": "string"
          },
          "title": "Allowedsides",
          "type": "array"
        },
        "maxOpenPositions": {
          "anyOf": [
            {
              "minimum": 1,
              "type": "integer"
            },
            {
              "type": "null"
            }
          ],
          "default": null,
          "title": "Maxopenpositions"
        },
        "maxSinglePositionExposure": {
          "anyOf": [
            {
              "$ref": "#/$defs/BrokerPositionSizeLimit"
            },
            {
              "type": "null"
            }
          ],
          "default": null
        },
        "requireOrderConfirmation": {
          "default": false,
          "title": "Requireorderconfirmation",
          "type": "boolean"
        }
      },
      "title": "BrokerTradingPolicy",
      "type": "object"
    }
  },
  "additionalProperties": false,
  "properties": {
    "account": {
      "$ref": "#/$defs/BrokerAccountSummary"
    },
    "audit": {
      "anyOf": [
        {
          "$ref": "#/$defs/BrokerAccountConfigurationAuditRecord"
        },
        {
          "type": "null"
        }
      ],
      "default": null
    },
    "configuration": {
      "anyOf": [
        {
          "$ref": "#/$defs/BrokerAccountConfiguration"
        },
        {
          "type": "null"
        }
      ],
      "default": null
    },
    "created": {
      "default": true,
      "title": "Created",
      "type": "boolean"
    },
    "generatedAt": {
      "anyOf": [
        {
          "format": "date-time",
          "type": "string"
        },
        {
          "type": "null"
        }
      ],
      "default": null,
      "title": "Generatedat"
    },
    "message": {
      "default": "",
      "title": "Message",
      "type": "string"
    },
    "reenabled": {
      "default": false,
      "title": "Reenabled",
      "type": "boolean"
    },
    "refreshAction": {
      "anyOf": [
        {
          "$ref": "#/$defs/BrokerAccountActionResponse"
        },
        {
          "type": "null"
        }
      ],
      "default": null
    }
  },
  "required": [
    "account"
  ],
  "title": "BrokerAccountOnboardingResponse",
  "type": "object"
}
