{
  "additionalProperties": false,
  "properties": {
    "above_sma_50": {
      "anyOf": [
        {
          "type": "boolean"
        },
        {
          "type": "null"
        }
      ],
      "default": null,
      "title": "Above Sma 50"
    },
    "as_of": {
      "anyOf": [
        {
          "format": "date",
          "type": "string"
        },
        {
          "type": "null"
        }
      ],
      "default": null,
      "title": "As Of"
    },
    "countries": {
      "anyOf": [
        {
          "items": {
            "type": "string"
          },
          "type": "array"
        },
        {
          "type": "null"
        }
      ],
      "default": null,
      "title": "Countries"
    },
    "direction": {
      "default": "desc",
      "enum": [
        "asc",
        "desc"
      ],
      "title": "Direction",
      "type": "string"
    },
    "has_gold": {
      "anyOf": [
        {
          "type": "boolean"
        },
        {
          "type": "null"
        }
      ],
      "default": null,
      "title": "Has Gold"
    },
    "has_silver": {
      "anyOf": [
        {
          "type": "boolean"
        },
        {
          "type": "null"
        }
      ],
      "default": null,
      "title": "Has Silver"
    },
    "industries": {
      "anyOf": [
        {
          "items": {
            "type": "string"
          },
          "type": "array"
        },
        {
          "type": "null"
        }
      ],
      "default": null,
      "title": "Industries"
    },
    "is_optionable": {
      "anyOf": [
        {
          "type": "boolean"
        },
        {
          "type": "null"
        }
      ],
      "default": null,
      "title": "Is Optionable"
    },
    "limit": {
      "default": 250,
      "maximum": 2000,
      "minimum": 1,
      "title": "Limit",
      "type": "integer"
    },
    "max_atr_14d": {
      "anyOf": [
        {
          "type": "number"
        },
        {
          "type": "null"
        }
      ],
      "default": null,
      "title": "Max Atr 14D"
    },
    "max_bb_width_20d": {
      "anyOf": [
        {
          "type": "number"
        },
        {
          "type": "null"
        }
      ],
      "default": null,
      "title": "Max Bb Width 20D"
    },
    "max_close": {
      "anyOf": [
        {
          "type": "number"
        },
        {
          "type": "null"
        }
      ],
      "default": null,
      "title": "Max Close"
    },
    "max_compression_score": {
      "anyOf": [
        {
          "type": "number"
        },
        {
          "type": "null"
        }
      ],
      "default": null,
      "title": "Max Compression Score"
    },
    "max_drawdown_1y": {
      "anyOf": [
        {
          "type": "number"
        },
        {
          "type": "null"
        }
      ],
      "default": null,
      "title": "Max Drawdown 1Y"
    },
    "max_gap_atr": {
      "anyOf": [
        {
          "type": "number"
        },
        {
          "type": "null"
        }
      ],
      "default": null,
      "title": "Max Gap Atr"
    },
    "max_return_1d": {
      "anyOf": [
        {
          "type": "number"
        },
        {
          "type": "null"
        }
      ],
      "default": null,
      "title": "Max Return 1D"
    },
    "max_return_5d": {
      "anyOf": [
        {
          "type": "number"
        },
        {
          "type": "null"
        }
      ],
      "default": null,
      "title": "Max Return 5D"
    },
    "max_sma_200d": {
      "anyOf": [
        {
          "type": "number"
        },
        {
          "type": "null"
        }
      ],
      "default": null,
      "title": "Max Sma 200D"
    },
    "max_sma_50d": {
      "anyOf": [
        {
          "type": "number"
        },
        {
          "type": "null"
        }
      ],
      "default": null,
      "title": "Max Sma 50D"
    },
    "max_trend_50_200": {
      "anyOf": [
        {
          "type": "number"
        },
        {
          "type": "null"
        }
      ],
      "default": null,
      "title": "Max Trend 50 200"
    },
    "max_vol_20d": {
      "anyOf": [
        {
          "type": "number"
        },
        {
          "type": "null"
        }
      ],
      "default": null,
      "title": "Max Vol 20D"
    },
    "max_volume": {
      "anyOf": [
        {
          "type": "number"
        },
        {
          "type": "null"
        }
      ],
      "default": null,
      "title": "Max Volume"
    },
    "max_volume_pct_rank_252d": {
      "anyOf": [
        {
          "type": "number"
        },
        {
          "type": "null"
        }
      ],
      "default": null,
      "title": "Max Volume Pct Rank 252D"
    },
    "max_volume_z_20d": {
      "anyOf": [
        {
          "type": "number"
        },
        {
          "type": "null"
        }
      ],
      "default": null,
      "title": "Max Volume Z 20D"
    },
    "min_atr_14d": {
      "anyOf": [
        {
          "type": "number"
        },
        {
          "type": "null"
        }
      ],
      "default": null,
      "title": "Min Atr 14D"
    },
    "min_bb_width_20d": {
      "anyOf": [
        {
          "type": "number"
        },
        {
          "type": "null"
        }
      ],
      "default": null,
      "title": "Min Bb Width 20D"
    },
    "min_close": {
      "anyOf": [
        {
          "type": "number"
        },
        {
          "type": "null"
        }
      ],
      "default": null,
      "title": "Min Close"
    },
    "min_compression_score": {
      "anyOf": [
        {
          "type": "number"
        },
        {
          "type": "null"
        }
      ],
      "default": null,
      "title": "Min Compression Score"
    },
    "min_drawdown_1y": {
      "anyOf": [
        {
          "type": "number"
        },
        {
          "type": "null"
        }
      ],
      "default": null,
      "title": "Min Drawdown 1Y"
    },
    "min_gap_atr": {
      "anyOf": [
        {
          "type": "number"
        },
        {
          "type": "null"
        }
      ],
      "default": null,
      "title": "Min Gap Atr"
    },
    "min_return_1d": {
      "anyOf": [
        {
          "type": "number"
        },
        {
          "type": "null"
        }
      ],
      "default": null,
      "title": "Min Return 1D"
    },
    "min_return_5d": {
      "anyOf": [
        {
          "type": "number"
        },
        {
          "type": "null"
        }
      ],
      "default": null,
      "title": "Min Return 5D"
    },
    "min_sma_200d": {
      "anyOf": [
        {
          "type": "number"
        },
        {
          "type": "null"
        }
      ],
      "default": null,
      "title": "Min Sma 200D"
    },
    "min_sma_50d": {
      "anyOf": [
        {
          "type": "number"
        },
        {
          "type": "null"
        }
      ],
      "default": null,
      "title": "Min Sma 50D"
    },
    "min_trend_50_200": {
      "anyOf": [
        {
          "type": "number"
        },
        {
          "type": "null"
        }
      ],
      "default": null,
      "title": "Min Trend 50 200"
    },
    "min_vol_20d": {
      "anyOf": [
        {
          "type": "number"
        },
        {
          "type": "null"
        }
      ],
      "default": null,
      "title": "Min Vol 20D"
    },
    "min_volume": {
      "anyOf": [
        {
          "type": "number"
        },
        {
          "type": "null"
        }
      ],
      "default": null,
      "title": "Min Volume"
    },
    "min_volume_pct_rank_252d": {
      "anyOf": [
        {
          "type": "number"
        },
        {
          "type": "null"
        }
      ],
      "default": null,
      "title": "Min Volume Pct Rank 252D"
    },
    "min_volume_z_20d": {
      "anyOf": [
        {
          "type": "number"
        },
        {
          "type": "null"
        }
      ],
      "default": null,
      "title": "Min Volume Z 20D"
    },
    "offset": {
      "default": 0,
      "minimum": 0,
      "title": "Offset",
      "type": "integer"
    },
    "q": {
      "anyOf": [
        {
          "maxLength": 255,
          "type": "string"
        },
        {
          "type": "null"
        }
      ],
      "default": null,
      "title": "Q"
    },
    "sectors": {
      "anyOf": [
        {
          "items": {
            "type": "string"
          },
          "type": "array"
        },
        {
          "type": "null"
        }
      ],
      "default": null,
      "title": "Sectors"
    },
    "sort": {
      "default": "volume",
      "enum": [
        "symbol",
        "close",
        "volume",
        "return_1d",
        "return_5d",
        "vol_20d",
        "drawdown_1y",
        "atr_14d",
        "gap_atr",
        "sma_50d",
        "sma_200d",
        "trend_50_200",
        "above_sma_50",
        "bb_width_20d",
        "compression_score",
        "volume_z_20d",
        "volume_pct_rank_252d"
      ],
      "title": "Sort",
      "type": "string"
    }
  },
  "title": "StockScreenerRequest",
  "type": "object"
}
